reil/__init__.py
reil/_version.py
reil/agents/__init__.py
reil/agents/actor_critic.py
reil/agents/agent.py
reil/agents/agent_base.py
reil/agents/agent_demon.py
reil/agents/deep_q_learning.py
reil/agents/linear_regression_agent.py
reil/agents/proximal_policy_optimization.py
reil/agents/q_learning.py
reil/agents/random_agent.py
reil/agents/user_agent.py
reil/datatypes/__init__.py
reil/datatypes/buffers/__init__.py
reil/datatypes/buffers/buffer.py
reil/datatypes/buffers/circular_buffer.py
reil/datatypes/buffers/endless_buffer.py
reil/datatypes/buffers/fill_flush_buffer.py
reil/datatypes/buffers/sink.py
reil/datatypes/buffers/vanilla_experience_replay.py
reil/datatypes/components.py
reil/datatypes/dataclasses.py
reil/datatypes/entity_register.py
reil/datatypes/feature.py
reil/datatypes/feature_array_dumper.py
reil/datatypes/mock_statistic.py
reil/environments/__init__.py
reil/environments/environment.py
reil/environments/sequential.py
reil/environments/session.py
reil/environments/session_builder.py
reil/environments/single.py
reil/environments/task.py
reil/environments/trajectory.py
reil/healthcare/__init__.py
reil/healthcare/agents/__init__.py
reil/healthcare/agents/warfarin_agent.py
reil/healthcare/dosing_protocols/__init__.py
reil/healthcare/dosing_protocols/dosing_protocol.py
reil/healthcare/dosing_protocols/three_phase_dosing_protocol.py
reil/healthcare/dosing_protocols/warfarin/__init__.py
reil/healthcare/dosing_protocols/warfarin/aurora.py
reil/healthcare/dosing_protocols/warfarin/gage.py
reil/healthcare/dosing_protocols/warfarin/intermountain.py
reil/healthcare/dosing_protocols/warfarin/iwpc.py
reil/healthcare/dosing_protocols/warfarin/lenzini.py
reil/healthcare/dosing_protocols/warfarin/ravvaz_dosing_protocols.py
reil/healthcare/mathematical_models/__init__.py
reil/healthcare/mathematical_models/hamberg_pkpd.py
reil/healthcare/mathematical_models/hamberg_pkpd_2010.py
reil/healthcare/mathematical_models/hamberg_pkpd_tf.py
reil-0.1.9.dist-info/LICENSE
reil-0.1.9.dist-info/WHEEL
reil-0.1.9.dist-info/METADATA
reil-0.1.9.dist-info/RECORD
