Metadata-Version: 2.1
Name: reil
Version: 0.1.9
Summary: 
License: MIT
Author: sanzabizadeh
Author-email: sadjad-anzabizadeh@uiowa.edu
Requires-Python: >=3.8,<3.11
Classifier: License :: OSI Approved :: MIT License
Classifier: Programming Language :: Python :: 3
Classifier: Programming Language :: Python :: 3.10
Classifier: Programming Language :: Python :: 3.8
Classifier: Programming Language :: Python :: 3.9
Requires-Dist: Keras-Applications (>=1.0.8,<2.0.0)
Requires-Dist: Keras-Preprocessing (>=1.1.2,<2.0.0)
Requires-Dist: Markdown (>=3.3.6,<4.0.0)
Requires-Dist: Pillow (>=9.0.0,<10.0.0)
Requires-Dist: Werkzeug (>=2.0.2,<3.0.0)
Requires-Dist: absl-py (==0.15.0)
Requires-Dist: astor (>=0.8.1,<0.9.0)
Requires-Dist: astroid (==2.7.2)
Requires-Dist: colorama (>=0.4.4,<0.5.0)
Requires-Dist: cycler (>=0.11.0,<0.12.0)
Requires-Dist: dill (>=0.3.4,<0.4.0)
Requires-Dist: gast (==0.3.3)
Requires-Dist: google-pasta (>=0.2.0,<0.3.0)
Requires-Dist: grpcio (==1.32)
Requires-Dist: h5py (==2.10)
Requires-Dist: importlib-metadata (>=4.10.1,<5.0.0)
Requires-Dist: isort (>=5.10.1,<6.0.0)
Requires-Dist: kiwisolver (>=1.3.2,<2.0.0)
Requires-Dist: lazy-object-proxy (>=1.7.1,<2.0.0)
Requires-Dist: matplotlib (>=3.5.1,<4.0.0)
Requires-Dist: mccabe (>=0.6.1,<0.7.0)
Requires-Dist: numpy (==1.19.2)
Requires-Dist: openpyxl (>=3.0.9,<4.0.0)
Requires-Dist: opt-einsum (>=3.3.0,<4.0.0)
Requires-Dist: pandas (==1.2)
Requires-Dist: protobuf (>=3.19.3,<4.0.0)
Requires-Dist: pyparsing (>=3.0.6,<4.0.0)
Requires-Dist: python-dateutil (>=2.8.2,<3.0.0)
Requires-Dist: pytz (>=2021.3,<2022.0)
Requires-Dist: ruamel.yaml (>=0.17.20,<0.18.0)
Requires-Dist: scikit-learn (>=1.0.2,<2.0.0)
Requires-Dist: scipy (>=1.7.3,<2.0.0)
Requires-Dist: six (==1.15)
Requires-Dist: tensorboard (>=2.7.0,<3.0.0)
Requires-Dist: tensorflow (==2.4.1)
Requires-Dist: tensorflow-estimator (==2.4)
Requires-Dist: tensorflow-probability (==0.12.2)
Requires-Dist: termcolor (>=1.1.0,<2.0.0)
Requires-Dist: versioneer (>=0.21,<0.22)
Requires-Dist: wrapt (==1.12.1)
Requires-Dist: zipp (>=3.7.0,<4.0.0)
